LICENSE.txt
froi/__init__.py
froi/exceptions.py
froi/froi.py
froi/route.py
froi-0.4.7.dist-info/LICENSE.txt
froi-0.4.7.dist-info/WHEEL
froi-0.4.7.dist-info/METADATA
froi-0.4.7.dist-info/RECORD
