Metadata-Version: 2.1
Name: froi
Version: 0.4.7
Summary: A Flask wrapper to easily handle routes defined as Python native objects
Home-page: https://github.com/mamerisawesome/froi
License: MIT
Keywords: flask wrapper,router,router interface,interface,wrapper
Author: Almer Mendoza
Author-email: atmalmer23@gmail.com
Requires-Python: >=3.6,<4.0
Classifier: License :: OSI Approved :: MIT License
Classifier: Programming Language :: Python :: 3
Classifier: Programming Language :: Python :: 3.6
Classifier: Programming Language :: Python :: 3.7
Requires-Dist: flask (>=1.0,<2.0)
Project-URL: Repository, https://github.com/mamerisawesome/froi
